hurricanerisk/__init__.py
hurricanerisk/hurricanerisk.py
HurricaneRisk-0.2.0.dist-info/METADATA
HurricaneRisk-0.2.0.dist-info/WHEEL
HurricaneRisk-0.2.0.dist-info/top_level.txt
HurricaneRisk-0.2.0.dist-info/RECORD
