Metadata-Version: 2.1
Name: HurricaneRisk
Version: 0.2.0
Summary: A library to analyze and visualize hurricane risk
Author: Scott
Classifier: Programming Language :: Python :: 3
Classifier: License :: OSI Approved :: MIT License
Classifier: Operating System :: OS Independent
Requires-Python: >=3.6
Requires-Dist: geopandas
Requires-Dist: shapely
Requires-Dist: requests
Requires-Dist: pandas
Requires-Dist: openpyxl
